complexoperations/JustSomeMath.py
complexoperations/__init__.py
test/test_JustSomeMath.py
complexoperations_niltonfernandes-0.0.2.dist-info/METADATA
complexoperations_niltonfernandes-0.0.2.dist-info/WHEEL
complexoperations_niltonfernandes-0.0.2.dist-info/top_level.txt
complexoperations_niltonfernandes-0.0.2.dist-info/RECORD
