Metadata-Version: 2.1
Name: complexoperations_niltonfernandes
Version: 0.0.2
Summary: Complex operations package
Author-email: Nilton Fernandes <niltonfernandesj@gmail.com>
Project-URL: Homepage, https://github.com/niltonfernandesj/devops-python
Project-URL: Bug Tracker, https://github.com/niltonfernandesj/devops-python/issues
Classifier: Programming Language :: Python :: 3
Classifier: License :: OSI Approved :: MIT License
Classifier: Operating System :: OS Independent
Requires-Python: >=3.9
